ddd-seedwork/__init__.py
ddd-seedwork/domain/Entity.py
ddd-seedwork/domain/Exceptions.py
ddd-seedwork/domain/__init__.py
ddd-seedwork/dto/DTO.py
ddd-seedwork/dto/__init__.py
ddd-seedwork/flask/ApiResponse.py
ddd-seedwork/flask/ErrorHandlers.py
ddd-seedwork/flask/__init__.py
ddd-seedwork/persistence/Exceptions.py
ddd-seedwork/persistence/Repository.py
ddd-seedwork/persistence/__init__.py
ddd_seedwork/__init__.py
ddd_seedwork/domain/Entity.py
ddd_seedwork/domain/Exceptions.py
ddd_seedwork/domain/__init__.py
ddd_seedwork/dto/DTO.py
ddd_seedwork/dto/__init__.py
ddd_seedwork/flask/ApiResponse.py
ddd_seedwork/flask/ErrorHandlers.py
ddd_seedwork/flask/__init__.py
ddd_seedwork/persistence/Exceptions.py
ddd_seedwork/persistence/Repository.py
ddd_seedwork/persistence/__init__.py
src/__init__.py
src/ddd-seedwork/__init__.py
src/ddd-seedwork/domain/Entity.py
src/ddd-seedwork/domain/Exceptions.py
src/ddd-seedwork/domain/__init__.py
src/ddd-seedwork/dto/DTO.py
src/ddd-seedwork/dto/__init__.py
src/ddd-seedwork/flask/ApiResponse.py
src/ddd-seedwork/flask/ErrorHandlers.py
src/ddd-seedwork/flask/__init__.py
src/ddd-seedwork/persistence/Exceptions.py
src/ddd-seedwork/persistence/Repository.py
src/ddd-seedwork/persistence/__init__.py
ddd_seedwork-0.0.1.dist-info/LICENSE
ddd_seedwork-0.0.1.dist-info/METADATA
ddd_seedwork-0.0.1.dist-info/WHEEL
ddd_seedwork-0.0.1.dist-info/top_level.txt
ddd_seedwork-0.0.1.dist-info/RECORD
